example_pkg/__init__.py
example_pkg/__main__.py
example_pkg/config.txt
example_pkg/mod1.py
example_pkg/mod2.py
example_pkg_willygoodwill-1.0.4.dist-info/DESCRIPTION.rst
example_pkg_willygoodwill-1.0.4.dist-info/METADATA
example_pkg_willygoodwill-1.0.4.dist-info/RECORD
example_pkg_willygoodwill-1.0.4.dist-info/WHEEL
example_pkg_willygoodwill-1.0.4.dist-info/entry_points.txt
example_pkg_willygoodwill-1.0.4.dist-info/metadata.json
example_pkg_willygoodwill-1.0.4.dist-info/top_level.txt
