Metadata-Version: 2.0
Name: example-pkg-willygoodwill
Version: 1.0.4
Summary: A small example package
Home-page: UNKNOWN
Author: Olga Lazunina
Author-email: olga.lazunina@gmail.com
License: UNKNOWN
Platform: UNKNOWN
Classifier: Programming Language :: Python :: 3
Classifier: License :: OSI Approved :: MIT License
Classifier: Operating System :: OS Independent
Requires-Python: >=3.6
